odoo9_addon_account_due_list_payment_mode-9.0.1.0.0.99.dev3-py2.7-nspkg.pth
odoo9_addon_account_due_list_payment_mode-9.0.1.0.0.99.dev3.dist-info/METADATA
odoo9_addon_account_due_list_payment_mode-9.0.1.0.0.99.dev3.dist-info/RECORD
odoo9_addon_account_due_list_payment_mode-9.0.1.0.0.99.dev3.dist-info/WHEEL
odoo9_addon_account_due_list_payment_mode-9.0.1.0.0.99.dev3.dist-info/namespace_packages.txt
odoo9_addon_account_due_list_payment_mode-9.0.1.0.0.99.dev3.dist-info/top_level.txt
odoo_addons/account_due_list_payment_mode/README.rst
odoo_addons/account_due_list_payment_mode/__init__.py
odoo_addons/account_due_list_payment_mode/__openerp__.py
odoo_addons/account_due_list_payment_mode/i18n/es.po
odoo_addons/account_due_list_payment_mode/models/__init__.py
odoo_addons/account_due_list_payment_mode/models/account_move_line.py
odoo_addons/account_due_list_payment_mode/static/description/icon.png
odoo_addons/account_due_list_payment_mode/views/payment_view.xml
